pyconstruct/__init__.py
pyconstruct/datasets/__init__.py
pyconstruct/datasets/base.py
pyconstruct/datasets/conll00.py
pyconstruct/datasets/equations.py
pyconstruct/datasets/ocr.py
pyconstruct/datasets/utils.py
pyconstruct/domains/__init__.py
pyconstruct/domains/base.py
pyconstruct/domains/minizinc.py
pyconstruct/domains/predefined/__init__.py
pyconstruct/domains/predefined/conll00.pmzn
pyconstruct/domains/predefined/ocr.pmzn
pyconstruct/domains/predefined/pyconstruct.pmzn
pyconstruct/domains/share/__init__.py
pyconstruct/domains/share/chain.pmzn
pyconstruct/domains/share/globals.pmzn
pyconstruct/domains/share/linear.pmzn
pyconstruct/domains/share/metrics.pmzn
pyconstruct/learners/__init__.py
pyconstruct/learners/base.py
pyconstruct/learners/cuttingplane.py
pyconstruct/learners/frankwolfe.py
pyconstruct/learners/perceptron.py
pyconstruct/learners/project.py
pyconstruct/learners/subgradient.py
pyconstruct/metrics/__init__.py
pyconstruct/metrics/losses.py
pyconstruct/models/__init__.py
pyconstruct/models/base.py
pyconstruct/utils/__init__.py
pyconstruct/utils/arrays.py
pyconstruct/utils/cache.py
pyconstruct/utils/dicts.py
pyconstruct/utils/logging.py
pyconstruct/utils/others.py
pyconstruct/utils/pickle.py
pyconstruct-0.2.2.dist-info/METADATA
pyconstruct-0.2.2.dist-info/RECORD
pyconstruct-0.2.2.dist-info/WHEEL
pyconstruct-0.2.2.dist-info/top_level.txt
