Metadata-Version: 2.1
Name: pyconstruct
Version: 0.2.2
Summary: A framework for declarative, constrained, structured-output prediction.
Home-page: https://github.com/unitn-sml/pyconstruct
Author: Paolo Dragone,Stefano Teso,Andrea Passerini
Author-email: dragone.paolo@gmail.com,stefano.teso@gmail.com,andrea.passerini@unitn.it
License: MIT
Platform: any
Classifier: Programming Language :: Python
Classifier: Programming Language :: Python :: 2
Classifier: Programming Language :: Python :: 2.7
Classifier: Programming Language :: Python :: 3
Classifier: Programming Language :: Python :: 3.5
Classifier: Development Status :: 4 - Beta
Classifier: Natural Language :: English
Classifier: Environment :: Console
Classifier: Intended Audience :: Developers
Classifier: License :: OSI Approved :: MIT License
Classifier: Operating System :: OS Independent
Classifier: Topic :: Software Development :: Libraries :: Python Modules
Requires-Dist: numpy
Requires-Dist: scipy
Requires-Dist: sklearn
Requires-Dist: pymzn
Requires-Dist: appdirs
Requires-Dist: jinja2
Requires-Dist: cachetools
